<?xml version="1.0"?>
<!DOCTYPE GraphCollection SYSTEM "http://www.inf.unibz.it/~blumenthal/dtd/GraphCollection.dtd">
<GraphCollection>
	<graph file="23141.gxl" class="i"/>
	<graph file="33570.gxl" class="a"/>
	<graph file="4881.gxl" class="i"/>
	<graph file="15752.gxl" class="a"/>
	<graph file="41681.gxl" class="i"/>
	<graph file="1218.gxl" class="a"/>
	<graph file="5592.gxl" class="i"/>
	<graph file="39374.gxl" class="i"/>
	<graph file="92.gxl" class="i"/>
	<graph file="15.gxl" class="i"/>
	<graph file="20693.gxl" class="i"/>
	<graph file="14562.gxl" class="i"/>
	<graph file="25917.gxl" class="a"/>
	<graph file="20691.gxl" class="i"/>
	<graph file="34266.gxl" class="i"/>
	<graph file="16979.gxl" class="a"/>
	<graph file="30418.gxl" class="a"/>
	<graph file="22994.gxl" class="i"/>
	<graph file="30025.gxl" class="i"/>
	<graph file="13371.gxl" class="i"/>
	<graph file="12538.gxl" class="i"/>
	<graph file="973.gxl" class="i"/>
	<graph file="15429.gxl" class="i"/>
	<graph file="3058.gxl" class="i"/>
	<graph file="11099.gxl" class="i"/>
	<graph file="1570.gxl" class="i"/>
	<graph file="1404.gxl" class="i"/>
	<graph file="27985.gxl" class="a"/>
	<graph file="29586.gxl" class="i"/>
	<graph file="1017.gxl" class="i"/>
	<graph file="648.gxl" class="i"/>
	<graph file="4178.gxl" class="i"/>
	<graph file="40760.gxl" class="i"/>
	<graph file="1732.gxl" class="i"/>
	<graph file="10515.gxl" class="a"/>
	<graph file="40931.gxl" class="a"/>
	<graph file="17167.gxl" class="i"/>
	<graph file="21559.gxl" class="a"/>
	<graph file="10973.gxl" class="i"/>
	<graph file="41803.gxl" class="a"/>
	<graph file="11147.gxl" class="i"/>
	<graph file="5015.gxl" class="i"/>
	<graph file="2291.gxl" class="i"/>
	<graph file="1769.gxl" class="i"/>
	<graph file="252.gxl" class="i"/>
	<graph file="14315.gxl" class="i"/>
	<graph file="21557.gxl" class="a"/>
	<graph file="25357.gxl" class="i"/>
	<graph file="6691.gxl" class="i"/>
	<graph file="14455.gxl" class="i"/>
	<graph file="15840.gxl" class="i"/>
	<graph file="35625.gxl" class="a"/>
	<graph file="12313.gxl" class="i"/>
	<graph file="34211.gxl" class="i"/>
	<graph file="28552.gxl" class="a"/>
	<graph file="2949.gxl" class="a"/>
	<graph file="10338.gxl" class="i"/>
	<graph file="17613.gxl" class="i"/>
	<graph file="10320.gxl" class="i"/>
	<graph file="25868.gxl" class="a"/>
	<graph file="18036.gxl" class="i"/>
	<graph file="2105.gxl" class="a"/>
	<graph file="3943.gxl" class="i"/>
	<graph file="27415.gxl" class="a"/>
	<graph file="11100.gxl" class="a"/>
	<graph file="23404.gxl" class="a"/>
	<graph file="5580.gxl" class="i"/>
	<graph file="8331.gxl" class="i"/>
	<graph file="10706.gxl" class="i"/>
	<graph file="30112.gxl" class="i"/>
	<graph file="36688.gxl" class="i"/>
	<graph file="1641.gxl" class="i"/>
	<graph file="262.gxl" class="i"/>
	<graph file="16664.gxl" class="i"/>
	<graph file="27469.gxl" class="a"/>
	<graph file="5650.gxl" class="i"/>
	<graph file="17587.gxl" class="i"/>
	<graph file="24419.gxl" class="i"/>
	<graph file="24420.gxl" class="i"/>
	<graph file="36531.gxl" class="i"/>
	<graph file="3701.gxl" class="i"/>
	<graph file="2688.gxl" class="i"/>
	<graph file="21873.gxl" class="i"/>
	<graph file="23493.gxl" class="i"/>
	<graph file="475.gxl" class="i"/>
	<graph file="16703.gxl" class="i"/>
	<graph file="35405.gxl" class="i"/>
	<graph file="27468.gxl" class="a"/>
	<graph file="1880.gxl" class="i"/>
	<graph file="15210.gxl" class="i"/>
	<graph file="6002.gxl" class="i"/>
	<graph file="14920.gxl" class="i"/>
	<graph file="34258.gxl" class="i"/>
	<graph file="10979.gxl" class="i"/>
	<graph file="10962.gxl" class="i"/>
	<graph file="7765.gxl" class="i"/>
	<graph file="14972.gxl" class="i"/>
	<graph file="9901.gxl" class="i"/>
	<graph file="14912.gxl" class="i"/>
	<graph file="9982.gxl" class="i"/>
	<graph file="6227.gxl" class="i"/>
	<graph file="1320.gxl" class="i"/>
	<graph file="9386.gxl" class="i"/>
	<graph file="1178.gxl" class="i"/>
	<graph file="25948.gxl" class="i"/>
	<graph file="16621.gxl" class="a"/>
	<graph file="25353.gxl" class="i"/>
	<graph file="28302.gxl" class="a"/>
	<graph file="31438.gxl" class="a"/>
	<graph file="4242.gxl" class="i"/>
	<graph file="2234.gxl" class="i"/>
	<graph file="11016.gxl" class="i"/>
	<graph file="12535.gxl" class="i"/>
	<graph file="14368.gxl" class="a"/>
	<graph file="18105.gxl" class="i"/>
	<graph file="30417.gxl" class="a"/>
	<graph file="1667.gxl" class="a"/>
	<graph file="21378.gxl" class="a"/>
	<graph file="6292.gxl" class="i"/>
	<graph file="29198.gxl" class="a"/>
	<graph file="3833.gxl" class="i"/>
	<graph file="8724.gxl" class="i"/>
	<graph file="17958.gxl" class="i"/>
	<graph file="23799.gxl" class="i"/>
	<graph file="40201.gxl" class="i"/>
	<graph file="11041.gxl" class="i"/>
	<graph file="28597.gxl" class="i"/>
	<graph file="5298.gxl" class="i"/>
	<graph file="13816.gxl" class="i"/>
	<graph file="6261.gxl" class="i"/>
	<graph file="1712.gxl" class="i"/>
	<graph file="9834.gxl" class="i"/>
	<graph file="21989.gxl" class="a"/>
	<graph file="27614.gxl" class="a"/>
	<graph file="42358.gxl" class="a"/>
	<graph file="28336.gxl" class="i"/>
	<graph file="27983.gxl" class="a"/>
	<graph file="4897.gxl" class="i"/>
	<graph file="21831.gxl" class="i"/>
	<graph file="31897.gxl" class="i"/>
	<graph file="11888.gxl" class="a"/>
	<graph file="16981.gxl" class="a"/>
	<graph file="23533.gxl" class="i"/>
	<graph file="12542.gxl" class="i"/>
	<graph file="3317.gxl" class="i"/>
	<graph file="1857.gxl" class="i"/>
	<graph file="20087.gxl" class="a"/>
	<graph file="32363.gxl" class="i"/>
	<graph file="1105.gxl" class="i"/>
	<graph file="4464.gxl" class="i"/>
</GraphCollection>