<?xml version="1.0"?>
<!DOCTYPE GraphCollection SYSTEM "http://www.inf.unibz.it/~blumenthal/dtd/GraphCollection.dtd">
<GraphCollection>
	<graph file="23614.gxl" class="i"/>
	<graph file="1012.gxl" class="i"/>
	<graph file="10256.gxl" class="i"/>
	<graph file="9690.gxl" class="a"/>
	<graph file="36307.gxl" class="i"/>
	<graph file="3833.gxl" class="i"/>
	<graph file="2947.gxl" class="a"/>
	<graph file="4897.gxl" class="i"/>
	<graph file="18035.gxl" class="i"/>
	<graph file="22636.gxl" class="i"/>
	<graph file="7515.gxl" class="i"/>
	<graph file="27970.gxl" class="i"/>
	<graph file="28437.gxl" class="i"/>
	<graph file="8960.gxl" class="i"/>
	<graph file="3667.gxl" class="i"/>
	<graph file="6191.gxl" class="i"/>
	<graph file="11017.gxl" class="i"/>
	<graph file="35329.gxl" class="i"/>
	<graph file="873.gxl" class="i"/>
	<graph file="2554.gxl" class="a"/>
	<graph file="23889.gxl" class="i"/>
	<graph file="16871.gxl" class="i"/>
	<graph file="21760.gxl" class="i"/>
	<graph file="4493.gxl" class="i"/>
	<graph file="42160.gxl" class="a"/>
	<graph file="2688.gxl" class="i"/>
	<graph file="27304.gxl" class="a"/>
	<graph file="3128.gxl" class="i"/>
	<graph file="12461.gxl" class="i"/>
	<graph file="9386.gxl" class="i"/>
	<graph file="23527.gxl" class="i"/>
	<graph file="1437.gxl" class="i"/>
	<graph file="28915.gxl" class="i"/>
	<graph file="7444.gxl" class="i"/>
	<graph file="41423.gxl" class="i"/>
	<graph file="5040.gxl" class="i"/>
	<graph file="11092.gxl" class="a"/>
	<graph file="16598.gxl" class="i"/>
	<graph file="6153.gxl" class="i"/>
	<graph file="23754.gxl" class="a"/>
	<graph file="34215.gxl" class="i"/>
	<graph file="37148.gxl" class="i"/>
	<graph file="31148.gxl" class="i"/>
	<graph file="3616.gxl" class="i"/>
	<graph file="32488.gxl" class="a"/>
	<graph file="4591.gxl" class="i"/>
	<graph file="5641.gxl" class="i"/>
	<graph file="6262.gxl" class="i"/>
	<graph file="1320.gxl" class="i"/>
	<graph file="7575.gxl" class="i"/>
	<graph file="26550.gxl" class="a"/>
	<graph file="38.gxl" class="i"/>
	<graph file="130.gxl" class="i"/>
	<graph file="40760.gxl" class="i"/>
	<graph file="986.gxl" class="i"/>
	<graph file="23495.gxl" class="i"/>
	<graph file="15844.gxl" class="i"/>
	<graph file="6656.gxl" class="i"/>
	<graph file="3761.gxl" class="i"/>
	<graph file="9939.gxl" class="i"/>
	<graph file="21087.gxl" class="i"/>
	<graph file="65.gxl" class="i"/>
	<graph file="4962.gxl" class="i"/>
	<graph file="1918.gxl" class="i"/>
	<graph file="243.gxl" class="i"/>
	<graph file="24934.gxl" class="i"/>
	<graph file="2080.gxl" class="i"/>
	<graph file="41363.gxl" class="i"/>
	<graph file="30025.gxl" class="i"/>
	<graph file="5102.gxl" class="i"/>
	<graph file="2343.gxl" class="a"/>
	<graph file="25929.gxl" class="i"/>
	<graph file="17616.gxl" class="i"/>
	<graph file="37266.gxl" class="a"/>
	<graph file="10979.gxl" class="i"/>
	<graph file="2870.gxl" class="i"/>
	<graph file="7899.gxl" class="i"/>
	<graph file="1615.gxl" class="a"/>
	<graph file="11059.gxl" class="a"/>
	<graph file="34227.gxl" class="i"/>
	<graph file="11425.gxl" class="i"/>
	<graph file="771.gxl" class="i"/>
	<graph file="35181.gxl" class="i"/>
	<graph file="27322.gxl" class="i"/>
	<graph file="5581.gxl" class="i"/>
	<graph file="33085.gxl" class="i"/>
	<graph file="15752.gxl" class="a"/>
	<graph file="214.gxl" class="i"/>
	<graph file="11392.gxl" class="i"/>
	<graph file="56.gxl" class="i"/>
	<graph file="18093.gxl" class="i"/>
	<graph file="849.gxl" class="i"/>
	<graph file="24830.gxl" class="i"/>
	<graph file="2948.gxl" class="a"/>
	<graph file="36894.gxl" class="i"/>
	<graph file="30113.gxl" class="i"/>
	<graph file="24643.gxl" class="a"/>
	<graph file="27735.gxl" class="i"/>
	<graph file="23600.gxl" class="i"/>
	<graph file="27732.gxl" class="i"/>
	<graph file="29845.gxl" class="i"/>
	<graph file="35319.gxl" class="i"/>
	<graph file="17834.gxl" class="a"/>
	<graph file="6081.gxl" class="i"/>
	<graph file="18443.gxl" class="a"/>
	<graph file="10226.gxl" class="a"/>
	<graph file="28336.gxl" class="i"/>
	<graph file="11575.gxl" class="i"/>
	<graph file="20416.gxl" class="a"/>
	<graph file="2175.gxl" class="i"/>
	<graph file="18433.gxl" class="a"/>
	<graph file="33690.gxl" class="i"/>
	<graph file="1694.gxl" class="i"/>
	<graph file="973.gxl" class="i"/>
	<graph file="4805.gxl" class="i"/>
	<graph file="6223.gxl" class="i"/>
	<graph file="25256.gxl" class="i"/>
	<graph file="14286.gxl" class="i"/>
	<graph file="803.gxl" class="i"/>
	<graph file="42164.gxl" class="i"/>
	<graph file="10320.gxl" class="i"/>
	<graph file="21498.gxl" class="i"/>
	<graph file="36027.gxl" class="a"/>
	<graph file="36308.gxl" class="i"/>
	<graph file="1854.gxl" class="i"/>
	<graph file="14447.gxl" class="i"/>
	<graph file="2965.gxl" class="i"/>
	<graph file="14313.gxl" class="i"/>
	<graph file="23949.gxl" class="a"/>
	<graph file="22995.gxl" class="i"/>
	<graph file="11216.gxl" class="i"/>
	<graph file="32867.gxl" class="i"/>
	<graph file="46.gxl" class="i"/>
	<graph file="19632.gxl" class="i"/>
	<graph file="22209.gxl" class="a"/>
	<graph file="21147.gxl" class="a"/>
	<graph file="9275.gxl" class="i"/>
	<graph file="40595.gxl" class="a"/>
	<graph file="18531.gxl" class="i"/>
	<graph file="13072.gxl" class="i"/>
	<graph file="563.gxl" class="i"/>
	<graph file="1812.gxl" class="i"/>
	<graph file="11426.gxl" class="i"/>
	<graph file="14972.gxl" class="i"/>
	<graph file="4178.gxl" class="i"/>
	<graph file="12357.gxl" class="i"/>
	<graph file="32692.gxl" class="i"/>
	<graph file="12541.gxl" class="i"/>
	<graph file="16840.gxl" class="i"/>
	<graph file="451.gxl" class="i"/>
</GraphCollection>