<?xml version="1.0"?>
<!DOCTYPE GraphCollection SYSTEM "http://www.inf.unibz.it/~blumenthal/dtd/GraphCollection.dtd">
<GraphCollection>
	<graph file="11108.gxl" class="a"/>
	<graph file="30506.gxl" class="a"/>
	<graph file="24644.gxl" class="a"/>
	<graph file="20088.gxl" class="a"/>
	<graph file="23751.gxl" class="a"/>
	<graph file="30415.gxl" class="a"/>
	<graph file="35135.gxl" class="a"/>
	<graph file="42438.gxl" class="a"/>
	<graph file="28561.gxl" class="a"/>
	<graph file="16842.gxl" class="a"/>
	<graph file="19051.gxl" class="a"/>
	<graph file="5665.gxl" class="a"/>
	<graph file="21147.gxl" class="a"/>
	<graph file="449.gxl" class="a"/>
	<graph file="21379.gxl" class="a"/>
	<graph file="21989.gxl" class="a"/>
	<graph file="2007.gxl" class="a"/>
	<graph file="15752.gxl" class="a"/>
	<graph file="13023.gxl" class="a"/>
	<graph file="11888.gxl" class="a"/>
	<graph file="40629.gxl" class="a"/>
	<graph file="13653.gxl" class="a"/>
	<graph file="31639.gxl" class="a"/>
	<graph file="42350.gxl" class="a"/>
	<graph file="20076.gxl" class="a"/>
	<graph file="17835.gxl" class="a"/>
	<graph file="28794.gxl" class="a"/>
	<graph file="10622.gxl" class="a"/>
	<graph file="1555.gxl" class="a"/>
	<graph file="42156.gxl" class="a"/>
	<graph file="21557.gxl" class="a"/>
	<graph file="18855.gxl" class="a"/>
	<graph file="27782.gxl" class="a"/>
	<graph file="18853.gxl" class="a"/>
	<graph file="10934.gxl" class="a"/>
	<graph file="30505.gxl" class="a"/>
	<graph file="22159.gxl" class="a"/>
	<graph file="40595.gxl" class="a"/>
	<graph file="2956.gxl" class="a"/>
	<graph file="2554.gxl" class="a"/>
	<graph file="31439.gxl" class="a"/>
	<graph file="21992.gxl" class="a"/>
	<graph file="12560.gxl" class="a"/>
	<graph file="3003.gxl" class="a"/>
	<graph file="14359.gxl" class="a"/>
	<graph file="33103.gxl" class="a"/>
	<graph file="28795.gxl" class="a"/>
	<graph file="15366.gxl" class="a"/>
	<graph file="16979.gxl" class="a"/>
	<graph file="27891.gxl" class="a"/>
	<graph file="38940.gxl" class="a"/>
	<graph file="10515.gxl" class="a"/>
	<graph file="14368.gxl" class="a"/>
	<graph file="37271.gxl" class="a"/>
	<graph file="21559.gxl" class="a"/>
	<graph file="42160.gxl" class="a"/>
	<graph file="27414.gxl" class="a"/>
	<graph file="31256.gxl" class="a"/>
	<graph file="31631.gxl" class="a"/>
	<graph file="27890.gxl" class="a"/>
	<graph file="11092.gxl" class="a"/>
	<graph file="33815.gxl" class="a"/>
	<graph file="1665.gxl" class="a"/>
	<graph file="2951.gxl" class="a"/>
	<graph file="16180.gxl" class="a"/>
	<graph file="22605.gxl" class="a"/>
	<graph file="41565.gxl" class="a"/>
	<graph file="18443.gxl" class="a"/>
	<graph file="20646.gxl" class="a"/>
	<graph file="13642.gxl" class="a"/>
	<graph file="21986.gxl" class="a"/>
	<graph file="2954.gxl" class="a"/>
	<graph file="34363.gxl" class="a"/>
	<graph file="22208.gxl" class="a"/>
	<graph file="37272.gxl" class="a"/>
	<graph file="35137.gxl" class="a"/>
	<graph file="22525.gxl" class="a"/>
	<graph file="12677.gxl" class="a"/>
	<graph file="41186.gxl" class="a"/>
	<graph file="20416.gxl" class="a"/>
	<graph file="27933.gxl" class="a"/>
	<graph file="24733.gxl" class="a"/>
	<graph file="11521.gxl" class="a"/>
	<graph file="38188.gxl" class="a"/>
	<graph file="2947.gxl" class="a"/>
	<graph file="41689.gxl" class="a"/>
	<graph file="33519.gxl" class="a"/>
	<graph file="42363.gxl" class="a"/>
	<graph file="28378.gxl" class="a"/>
	<graph file="27889.gxl" class="a"/>
	<graph file="7993.gxl" class="a"/>
	<graph file="27304.gxl" class="a"/>
	<graph file="36027.gxl" class="a"/>
	<graph file="27783.gxl" class="a"/>
	<graph file="31511.gxl" class="a"/>
	<graph file="16974.gxl" class="a"/>
	<graph file="11166.gxl" class="a"/>
	<graph file="30418.gxl" class="a"/>
	<graph file="18433.gxl" class="a"/>
	<graph file="22209.gxl" class="a"/>
	<graph file="28863.gxl" class="a"/>
	<graph file="22733.gxl" class="a"/>
	<graph file="41883.gxl" class="a"/>
	<graph file="42357.gxl" class="a"/>
	<graph file="4697.gxl" class="a"/>
	<graph file="41542.gxl" class="a"/>
	<graph file="26550.gxl" class="a"/>
	<graph file="1217.gxl" class="a"/>
	<graph file="10680.gxl" class="a"/>
	<graph file="33132.gxl" class="a"/>
	<graph file="12480.gxl" class="a"/>
	<graph file="28302.gxl" class="a"/>
	<graph file="26764.gxl" class="a"/>
	<graph file="27468.gxl" class="a"/>
	<graph file="2553.gxl" class="a"/>
	<graph file="24642.gxl" class="a"/>
	<graph file="1218.gxl" class="a"/>
	<graph file="18437.gxl" class="a"/>
	<graph file="18432.gxl" class="a"/>
	<graph file="27985.gxl" class="a"/>
	<graph file="42157.gxl" class="a"/>
	<graph file="20032.gxl" class="a"/>
	<graph file="26430.gxl" class="a"/>
	<graph file="15749.gxl" class="a"/>
	<graph file="16981.gxl" class="a"/>
	<graph file="29128.gxl" class="a"/>
	<graph file="28867.gxl" class="a"/>
	<graph file="21684.gxl" class="a"/>
	<graph file="18788.gxl" class="a"/>
	<graph file="1605.gxl" class="a"/>
	<graph file="42154.gxl" class="a"/>
	<graph file="35625.gxl" class="a"/>
	<graph file="2949.gxl" class="a"/>
	<graph file="27416.gxl" class="a"/>
	<graph file="39262.gxl" class="a"/>
	<graph file="1613.gxl" class="a"/>
	<graph file="28551.gxl" class="a"/>
	<graph file="41885.gxl" class="a"/>
	<graph file="2008.gxl" class="a"/>
	<graph file="15750.gxl" class="a"/>
	<graph file="11059.gxl" class="a"/>
	<graph file="27469.gxl" class="a"/>
	<graph file="25868.gxl" class="a"/>
	<graph file="16621.gxl" class="a"/>
	<graph file="23754.gxl" class="a"/>
	<graph file="2343.gxl" class="a"/>
	<graph file="23333.gxl" class="a"/>
	<graph file="22207.gxl" class="a"/>
	<graph file="39873.gxl" class="a"/>
	<graph file="2948.gxl" class="a"/>
	<graph file="19749.gxl" class="i"/>
	<graph file="30003.gxl" class="i"/>
	<graph file="27322.gxl" class="i"/>
	<graph file="26423.gxl" class="i"/>
	<graph file="2205.gxl" class="i"/>
	<graph file="1636.gxl" class="i"/>
	<graph file="16260.gxl" class="i"/>
	<graph file="6006.gxl" class="i"/>
	<graph file="66.gxl" class="i"/>
	<graph file="1030.gxl" class="i"/>
	<graph file="34634.gxl" class="i"/>
	<graph file="247.gxl" class="i"/>
	<graph file="25359.gxl" class="i"/>
	<graph file="13072.gxl" class="i"/>
	<graph file="16664.gxl" class="i"/>
	<graph file="38966.gxl" class="i"/>
	<graph file="23528.gxl" class="i"/>
	<graph file="28513.gxl" class="i"/>
	<graph file="2128.gxl" class="i"/>
	<graph file="28336.gxl" class="i"/>
	<graph file="7204.gxl" class="i"/>
	<graph file="35385.gxl" class="i"/>
	<graph file="39570.gxl" class="i"/>
	<graph file="37715.gxl" class="i"/>
	<graph file="18531.gxl" class="i"/>
	<graph file="3363.gxl" class="i"/>
	<graph file="18931.gxl" class="i"/>
	<graph file="11563.gxl" class="i"/>
	<graph file="2277.gxl" class="i"/>
	<graph file="2144.gxl" class="i"/>
	<graph file="15840.gxl" class="i"/>
	<graph file="1026.gxl" class="i"/>
	<graph file="2480.gxl" class="i"/>
	<graph file="4342.gxl" class="i"/>
	<graph file="18080.gxl" class="i"/>
	<graph file="17532.gxl" class="i"/>
	<graph file="19619.gxl" class="i"/>
	<graph file="6449.gxl" class="i"/>
	<graph file="6801.gxl" class="i"/>
	<graph file="1541.gxl" class="i"/>
	<graph file="18038.gxl" class="i"/>
	<graph file="11575.gxl" class="i"/>
	<graph file="6701.gxl" class="i"/>
	<graph file="13051.gxl" class="i"/>
	<graph file="10245.gxl" class="i"/>
	<graph file="1205.gxl" class="i"/>
	<graph file="33112.gxl" class="i"/>
	<graph file="7515.gxl" class="i"/>
	<graph file="337.gxl" class="i"/>
	<graph file="7.gxl" class="i"/>
	<graph file="34848.gxl" class="i"/>
	<graph file="377.gxl" class="i"/>
	<graph file="10946.gxl" class="i"/>
	<graph file="5330.gxl" class="i"/>
	<graph file="28174.gxl" class="i"/>
	<graph file="4446.gxl" class="i"/>
	<graph file="7319.gxl" class="i"/>
	<graph file="2423.gxl" class="i"/>
	<graph file="11573.gxl" class="i"/>
	<graph file="26196.gxl" class="i"/>
	<graph file="4962.gxl" class="i"/>
	<graph file="335.gxl" class="i"/>
	<graph file="6643.gxl" class="i"/>
	<graph file="7724.gxl" class="i"/>
	<graph file="2244.gxl" class="i"/>
	<graph file="20700.gxl" class="i"/>
	<graph file="35997.gxl" class="i"/>
	<graph file="5102.gxl" class="i"/>
	<graph file="10293.gxl" class="i"/>
	<graph file="16840.gxl" class="i"/>
	<graph file="22044.gxl" class="i"/>
	<graph file="9600.gxl" class="i"/>
	<graph file="20682.gxl" class="i"/>
	<graph file="36600.gxl" class="i"/>
	<graph file="10102.gxl" class="i"/>
	<graph file="21828.gxl" class="i"/>
	<graph file="4901.gxl" class="i"/>
	<graph file="25256.gxl" class="i"/>
	<graph file="23122.gxl" class="i"/>
	<graph file="1383.gxl" class="i"/>
	<graph file="865.gxl" class="i"/>
	<graph file="8572.gxl" class="i"/>
	<graph file="25958.gxl" class="i"/>
	<graph file="34413.gxl" class="i"/>
	<graph file="537.gxl" class="i"/>
	<graph file="13340.gxl" class="i"/>
	<graph file="31897.gxl" class="i"/>
	<graph file="27210.gxl" class="i"/>
	<graph file="14927.gxl" class="i"/>
	<graph file="39964.gxl" class="i"/>
	<graph file="31112.gxl" class="i"/>
	<graph file="8628.gxl" class="i"/>
	<graph file="1493.gxl" class="i"/>
	<graph file="34938.gxl" class="i"/>
	<graph file="38056.gxl" class="i"/>
	<graph file="10858.gxl" class="i"/>
	<graph file="13307.gxl" class="i"/>
	<graph file="36657.gxl" class="i"/>
	<graph file="46.gxl" class="i"/>
	<graph file="7765.gxl" class="i"/>
	<graph file="23129.gxl" class="i"/>
	<graph file="18020.gxl" class="i"/>
	<graph file="1200.gxl" class="i"/>
	<graph file="10122.gxl" class="i"/>
	<graph file="8165.gxl" class="i"/>
	<graph file="3128.gxl" class="i"/>
	<graph file="1108.gxl" class="i"/>
	<graph file="718.gxl" class="i"/>
	<graph file="13014.gxl" class="i"/>
	<graph file="941.gxl" class="i"/>
	<graph file="37749.gxl" class="i"/>
	<graph file="1561.gxl" class="i"/>
	<graph file="37747.gxl" class="i"/>
	<graph file="422.gxl" class="i"/>
	<graph file="12427.gxl" class="i"/>
	<graph file="3883.gxl" class="i"/>
	<graph file="18036.gxl" class="i"/>
	<graph file="10962.gxl" class="i"/>
	<graph file="7899.gxl" class="i"/>
	<graph file="18930.gxl" class="i"/>
	<graph file="10338.gxl" class="i"/>
	<graph file="1540.gxl" class="i"/>
	<graph file="13239.gxl" class="i"/>
	<graph file="6931.gxl" class="i"/>
	<graph file="17570.gxl" class="i"/>
	<graph file="1776.gxl" class="i"/>
	<graph file="1419.gxl" class="i"/>
	<graph file="2325.gxl" class="i"/>
	<graph file="1315.gxl" class="i"/>
	<graph file="10320.gxl" class="i"/>
	<graph file="26416.gxl" class="i"/>
	<graph file="32167.gxl" class="i"/>
	<graph file="26527.gxl" class="i"/>
	<graph file="7575.gxl" class="i"/>
	<graph file="1080.gxl" class="i"/>
	<graph file="6616.gxl" class="i"/>
	<graph file="30.gxl" class="i"/>
	<graph file="11095.gxl" class="i"/>
	<graph file="21825.gxl" class="i"/>
	<graph file="262.gxl" class="i"/>
	<graph file="7005.gxl" class="i"/>
	<graph file="27859.gxl" class="i"/>
	<graph file="13231.gxl" class="i"/>
	<graph file="29440.gxl" class="i"/>
	<graph file="38975.gxl" class="i"/>
	<graph file="4805.gxl" class="i"/>
	<graph file="10255.gxl" class="i"/>
	<graph file="8331.gxl" class="i"/>
	<graph file="914.gxl" class="i"/>
	<graph file="263.gxl" class="i"/>
</GraphCollection>