<?xml version="1.0"?>
<!DOCTYPE GraphCollection SYSTEM "http://www.inf.unibz.it/~blumenthal/dtd/GraphCollection.dtd">
<GraphCollection>
	<graph file="molecule_2574.gxl" class="mutagen"/>
	<graph file="molecule_2681.gxl" class="mutagen"/>
	<graph file="molecule_2433.gxl" class="nonmutagen"/>
	<graph file="molecule_2569.gxl" class="nonmutagen"/>
	<graph file="molecule_2602.gxl" class="nonmutagen"/>
	<graph file="molecule_2844.gxl" class="nonmutagen"/>
	<graph file="molecule_2908.gxl" class="nonmutagen"/>
	<graph file="molecule_3290.gxl" class="mutagen"/>
	<graph file="molecule_3994.gxl" class="mutagen"/>
	<graph file="molecule_3997.gxl" class="mutagen"/>
	<graph file="molecule_3998.gxl" class="mutagen"/>
	<graph file="molecule_4001.gxl" class="mutagen"/>
	<graph file="molecule_4014.gxl" class="mutagen"/>
	<graph file="molecule_4043.gxl" class="mutagen"/>
	<graph file="molecule_4230.gxl" class="mutagen"/>
	<graph file="molecule_4316.gxl" class="mutagen"/>
	<graph file="molecule_2981.gxl" class="nonmutagen"/>
	<graph file="molecule_3090.gxl" class="nonmutagen"/>
	<graph file="molecule_3249.gxl" class="nonmutagen"/>
	<graph file="molecule_3309.gxl" class="nonmutagen"/>
	<graph file="molecule_3329.gxl" class="nonmutagen"/>
	<graph file="molecule_3485.gxl" class="nonmutagen"/>
	<graph file="molecule_3666.gxl" class="nonmutagen"/>
	<graph file="molecule_3768.gxl" class="nonmutagen"/>
	<graph file="molecule_3957.gxl" class="nonmutagen"/>
	<graph file="molecule_3981.gxl" class="nonmutagen"/>
	<graph file="molecule_3982.gxl" class="nonmutagen"/>
	<graph file="molecule_4075.gxl" class="nonmutagen"/>
	<graph file="molecule_4101.gxl" class="nonmutagen"/>
	<graph file="molecule_4107.gxl" class="nonmutagen"/>
	<graph file="molecule_4132.gxl" class="nonmutagen"/>
	<graph file="molecule_4145.gxl" class="nonmutagen"/>
	<graph file="molecule_4188.gxl" class="nonmutagen"/>
	<graph file="molecule_4238.gxl" class="nonmutagen"/>
	<graph file="molecule_4266.gxl" class="nonmutagen"/>
	<graph file="molecule_4284.gxl" class="nonmutagen"/>
	<graph file="molecule_4296.gxl" class="nonmutagen"/>
	<graph file="molecule_88.gxl" class="mutagen"/>
	<graph file="molecule_98.gxl" class="mutagen"/>
	<graph file="molecule_520.gxl" class="mutagen"/>
	<graph file="molecule_829.gxl" class="mutagen"/>
	<graph file="molecule_1575.gxl" class="mutagen"/>
	<graph file="molecule_2170.gxl" class="mutagen"/>
	<graph file="molecule_2273.gxl" class="mutagen"/>
	<graph file="molecule_154.gxl" class="nonmutagen"/>
	<graph file="molecule_255.gxl" class="nonmutagen"/>
	<graph file="molecule_553.gxl" class="nonmutagen"/>
	<graph file="molecule_666.gxl" class="nonmutagen"/>
	<graph file="molecule_935.gxl" class="nonmutagen"/>
	<graph file="molecule_1090.gxl" class="nonmutagen"/>
	<graph file="molecule_1183.gxl" class="nonmutagen"/>
	<graph file="molecule_1252.gxl" class="nonmutagen"/>
	<graph file="molecule_1379.gxl" class="nonmutagen"/>
	<graph file="molecule_1470.gxl" class="nonmutagen"/>
	<graph file="molecule_1527.gxl" class="nonmutagen"/>
	<graph file="molecule_1769.gxl" class="nonmutagen"/>
	<graph file="molecule_1811.gxl" class="nonmutagen"/>
	<graph file="molecule_2108.gxl" class="nonmutagen"/>
	<graph file="molecule_2324.gxl" class="nonmutagen"/>
	<graph file="molecule_2366.gxl" class="nonmutagen"/>
</GraphCollection>